ezwgd/Format/Sequence.py
ezwgd/GXF/GFFtools.py
ezwgd/__init__.py
ezwgd/coll/_corecoll.py
ezwgd/coll/powercoll.py
ezwgd/coll/somecoll.py
ezwgd/evo/dnds.py
ezwgd/frontend/PAML.py
ezwgd/frontend/__init__.py
ezwgd/frontend/frontend.py
ezwgd/help.py
ezwgd/pipeline/Collinearity.py
ezwgd/pipeline/__init__.py
ezwgd/plot/Coll.py
ezwgd/plot/__init__.py
ezwgd/plot/kaks.py
ezwgd/py.typed
ezwgd/tidy/reformat.py
ezwgd/tidy/rename.py
ezwgd/utils/__init__.py
ezwgd/utils/anywhere.py
ezwgd/utils/parse.py
ezwgd-0.0.12.dist-info/licenses/LICENSE
ezwgd-0.0.12.dist-info/WHEEL
ezwgd-0.0.12.dist-info/METADATA
ezwgd-0.0.12.dist-info/RECORD
