Metadata-Version: 2.4
Name: ezwgd
Version: 0.0.12
Summary: An easy-to-use bioinformatics toolbox for Whole-genome Compare Analysis, Especially for Whole-genome Duplicate (WGD) Events.
Author: hyli360
Author-email: hyli360 <lihuanyu2003@gmail.com>
License-Expression: GPL-3.0-only
License-File: LICENSE
Requires-Dist: biopython>=1.86
Requires-Dist: matplotlib>=3.10.8
Requires-Dist: numpy>=2.2.6
Requires-Dist: pandas>=2.3.3
Requires-Dist: pandas-stubs~=2.3.3
Requires-Dist: polars>=1.37.1
Requires-Dist: pyarrow>=23.0.0
Requires-Dist: rich>=14.2.0
Requires-Dist: scipy>=1.15.3
Requires-Python: >=3.10
